probnode/__init__.py
probnode/computation/__init__.py
probnode/computation/contract.py
probnode/computation/expand.py
probnode/computation/probability_contracting_logic.py
probnode/computation/probability_expanding_logic.py
probnode/computation/util.py
probnode/datatype/__init__.py
probnode/datatype/probability_distribution.py
probnode/datatype/probability_value.py
probnode/interface/__init__.py
probnode/interface/ievent.py
probnode/interface/ioutcome.py
probnode/interface/iset.py
probnode/probability/__init__.py
probnode/probability/event.py
probnode/probability/outcome.py
probnode/probability/probability_measure.py
probnode/probability/random_variable.py
probnode/probability/sample_space.py
probnode-0.2.4.dist-info/LICENSE.md
probnode-0.2.4.dist-info/METADATA
probnode-0.2.4.dist-info/WHEEL
probnode-0.2.4.dist-info/top_level.txt
probnode-0.2.4.dist-info/RECORD
