Metadata-Version: 2.1
Name: probnode
Version: 0.2.4
Summary: Probability expression library
Home-page: https://github.com/medasmarathon/Proba
Author: Duc Dang
Author-email: vinhduc91@outlook.com
Project-URL: Bug Tracker, https://github.com/medasmarathon/Proba/issues
Project-URL: Documentation, https://github.com/medasmarathon/Probnode/wiki
Classifier: Programming Language :: Python :: 3
Classifier: License :: OSI Approved :: BSD License
Classifier: Operating System :: OS Independent
Classifier: Intended Audience :: Science/Research
Classifier: Intended Audience :: Developers
Requires-Python: >=3.7
License-File: LICENSE.md
Requires-Dist: pyfields
